CHANGES.rst
CONTRIBUTORS.rst
MANIFEST.in
README.rst
setup.py
src/propertyshelf/__init__.py
src/propertyshelf.fabfile.common.egg-info/PKG-INFO
src/propertyshelf.fabfile.common.egg-info/SOURCES.txt
src/propertyshelf.fabfile.common.egg-info/dependency_links.txt
src/propertyshelf.fabfile.common.egg-info/entry_points.txt
src/propertyshelf.fabfile.common.egg-info/namespace_packages.txt
src/propertyshelf.fabfile.common.egg-info/not-zip-safe
src/propertyshelf.fabfile.common.egg-info/requires.txt
src/propertyshelf.fabfile.common.egg-info/top_level.txt
src/propertyshelf/fabfile/__init__.py
src/propertyshelf/fabfile/common/__init__.py
src/propertyshelf/fabfile/common/bootstrap.py
src/propertyshelf/fabfile/common/environments.py
src/propertyshelf/fabfile/common/exceptions.py
src/propertyshelf/fabfile/common/frontend.py
src/propertyshelf/fabfile/common/rackspace.py
src/propertyshelf/fabfile/common/roles.py
src/propertyshelf/fabfile/common/utils.py
src/propertyshelf/fabfile/common/zodb.py