Metadata-Version: 1.1
Name: propertyshelf.fabfile.common
Version: 0.1
Summary: Commonly used fabric commands.
Home-page: https://github.com/propertyshelf/propertyshelf.fabfile.common
Author: Propertyshelf, Inc.
Author-email: development@propertyshelf.com
License: BSD
Download-URL: http://pypi.python.org/pypi/propertyshelf.fabfile.common
Keywords: fabric python deployment
Platform: UNKNOWN
Classifier: Programming Language :: Python
